brownant/__init__.py
brownant/app.py
brownant/dinergate.py
brownant/exceptions.py
brownant/request.py
brownant/site.py
brownant/utils.py
brownant/pipeline/__init__.py
brownant/pipeline/base.py
brownant/pipeline/html.py
brownant/pipeline/network.py
brownant-0.1.6.dist-info/DESCRIPTION.rst
brownant-0.1.6.dist-info/METADATA
brownant-0.1.6.dist-info/metadata.json
brownant-0.1.6.dist-info/RECORD
brownant-0.1.6.dist-info/top_level.txt
brownant-0.1.6.dist-info/WHEEL
tests/test_pipeline/__init__.py
tests/test_pipeline/test_base.py
tests/test_pipeline/test_html.py
tests/test_pipeline/test_network.py
