Metadata-Version: 2.0
Name: brownant
Version: 0.1.6
Summary: A lightweight web data extracting framework.
Home-page: https://github.com/douban/brownant
Author: Subject-Dev Team, Douban Inc.
Author-email: subject-dev@douban.com
License: BSD
Keywords: extract,web data
Platform: UNKNOWN
Classifier: Programming Language :: Python
Classifier: Programming Language :: Python :: 2.7
Classifier: Programming Language :: Python :: 3.3
Classifier: Programming Language :: Python :: 3.4
Classifier: Programming Language :: Python :: Implementation :: PyPy
Classifier: Development Status :: 3 - Alpha
Classifier: License :: OSI Approved :: BSD License
Classifier: Intended Audience :: Developers
Classifier: Operating System :: OS Independent
Classifier: Environment :: Other Environment
Classifier: Topic :: Software Development :: Libraries :: Python Modules
Requires-Dist: Werkzeug (>=0.8)
Requires-Dist: requests (>=1.0)
Requires-Dist: six
Requires-Dist: lxml (>=3.1)
